chiavdf.cpython-314-aarch64-linux-gnu.so
chiavdf.libs/libgmp-ba17cf27.so.10.4.1
chiavdf.libs/libgmpxx-cb676085.so.4.6.1
chiavdf-1.1.14.dist-info/METADATA
chiavdf-1.1.14.dist-info/WHEEL
chiavdf-1.1.14.dist-info/top_level.txt
chiavdf-1.1.14.dist-info/RECORD
chiavdf-1.1.14.dist-info/licenses/LICENSE
