Metadata-Version: 2.4
Name: chiavdf
Version: 1.1.14
Summary: Chia vdf verification (wraps C++)
Home-page: https://github.com/Chia-Network/chiavdf
Author: Florin Chirica
Author-email: florin@chia.net
License: Apache-2.0
Requires-Python: >=3.9
License-File: LICENSE
Dynamic: author
Dynamic: author-email
Dynamic: description
Dynamic: description-content-type
Dynamic: home-page
Dynamic: license
Dynamic: license-file
Dynamic: requires-python
Dynamic: summary
